gradient_quality_control/__init__.py
gradient_quality_control/optimizer_utils.py
gradient_quality_control/py.typed
gradient_quality_control/base/__init__.py
gradient_quality_control/base/abstract_optimizer_wrapper.py
gradient_quality_control/base/distributed_metrics.py
gradient_quality_control/base/gradient_accumulation.py
gradient_quality_control/base/optimizer_mocking.py
gradient_quality_control/base/orchestrator.py
gradient_quality_control/base/reporting.py
gradient_quality_control/base/state_management.py
gradient_quality_control/implementations/__init__.py
gradient_quality_control/implementations/gradient_noise_scale.py
gradient_quality_control/implementations/gradient_norm_rescaler.py
gradient_quality_control/implementations/gradient_norm_threshold_scheduler.py
gradient_quality_control/implementations/metric_hypothesis_test.py
gradient_quality_control/implementations/schedule_batch_controller.py
torch_gqc-0.10.4.dist-info/licenses/LICENSE
torch_gqc-0.10.4.dist-info/METADATA
torch_gqc-0.10.4.dist-info/WHEEL
torch_gqc-0.10.4.dist-info/top_level.txt
torch_gqc-0.10.4.dist-info/RECORD
