Metadata-Version: 2.4
Name: torch-gqc
Version: 0.10.4
Summary: Adaptive gradient accumulation for improved training efficiency
Author-email: Christopher O'Quinn <chrisoquinn.2@gmail.com>
License: MIT
Project-URL: Homepage, https://github.com/smithblack-0/GradientQualityControl
Project-URL: Repository, https://github.com/smithblack-0/GradientQualityControl
Project-URL: Documentation, https://github.com/smithblack-0/GradientQualityControl
Keywords: deep-learning,pytorch,optimization,gradient-accumulation,training
Classifier: Development Status :: 4 - Beta
Classifier: Intended Audience :: Science/Research
Classifier: License :: OSI Approved :: MIT License
Classifier: Programming Language :: Python :: 3
Classifier: Programming Language :: Python :: 3.9
Classifier: Programming Language :: Python :: 3.10
Classifier: Programming Language :: Python :: 3.11
Classifier: Programming Language :: Python :: 3.12
Classifier: Topic :: Scientific/Engineering :: Artificial Intelligence
Requires-Python: >=3.9
License-File: LICENSE
Requires-Dist: torch>=2.0.0
Requires-Dist: numpy>=1.20.0
Requires-Dist: scipy>=1.7.0
Requires-Dist: torch-schedule-anything>=0.10.0
Provides-Extra: dev
Requires-Dist: pytest>=7.0; extra == "dev"
Requires-Dist: pytest-cov; extra == "dev"
Requires-Dist: black; extra == "dev"
Requires-Dist: ruff; extra == "dev"
Dynamic: license-file
